unitycatalog/ai/openai/__init__.py
unitycatalog/ai/openai/toolkit.py
unitycatalog/ai/openai/utils.py
unitycatalog/ai/openai/version.py
unitycatalog_openai-0.2.0.dist-info/METADATA
unitycatalog_openai-0.2.0.dist-info/WHEEL
unitycatalog_openai-0.2.0.dist-info/RECORD
