Metadata-Version: 2.4
Name: unitycatalog-openai
Version: 0.2.0
Summary: Support for Unity Catalog functions as OpenAI tools
Author-email: Serena Ruan <serena.ruan@databricks.com>
License: Apache-2.0
Requires-Python: >=3.9
Requires-Dist: openai>=1.46.1
Requires-Dist: pydantic<3,>=2
Requires-Dist: unitycatalog-ai
Provides-Extra: databricks
Requires-Dist: unitycatalog-ai[databricks]; extra == 'databricks'
Provides-Extra: databricks-dev
Requires-Dist: unitycatalog-ai[databricks-dev]; extra == 'databricks-dev'
Provides-Extra: dev
Requires-Dist: unitycatalog-ai[dev]; extra == 'dev'
